{
  "locks": {
    "englishlit": {
      "machine": "PCTOP",
      "time": 1780305707.4785745
    },
    "commerce": {
      "machine": "PCTOP",
      "time": 1780305707.59829
    },
    "irk": {
      "machine": "PCTOP",
      "time": 1780305668.4623878
    },
    "insurance": {
      "machine": "A-Server",
      "time": 1780303284.471029
    },
    "mathematics": {
      "machine": "PCTOP",
      "time": 1780305705.6781652
    },
    "english": {
      "machine": "PCTOP",
      "time": 1780305451.9862876
    },
    "physics": {
      "machine": "PCTOP",
      "time": 1780305669.2101405
    },
    "government": {
      "machine": "PCTOP",
      "time": 1780305711.0939267
    },
    "geography": {
      "machine": "PCTOP",
      "time": 1780305705.9920447
    },
    "accounting": {
      "machine": "PCTOP",
      "time": 1780305706.881846
    },
    "civiledu": {
      "machine": "PCTOP",
      "time": 1780305707.4043798
    },
    "crk": {
      "machine": "PCTOP",
      "time": 1780305684.5853074
    },
    "history": {
      "machine": "PCTOP",
      "time": 1780305668.5264444
    }
  }
}