[
  {
    "id": 16,
    "question": "The division of Nigeria into various constituencies with each electing a person to represent it in the National Assembly is a demonstration of",
    "option": {
      "a": "checks and balances",
      "b": "popular participation",
      "c": "political rivalry among the constituents",
      "d": "drive towards secession in the country."
    },
    "section": "",
    "image": "",
    "answer": "b",
    "solution": "",
    "examtype": "wassce",
    "examyear": "2014"
  },
  {
    "id": 23,
    "question": "To prevent the spread of HIV/AIDS, people should be encouraged to",
    "option": {
      "a": "avoid casual sexual activities",
      "b": "marry very early in life",
      "c": "engage in gainful employment",
      "d": "pursue higher education"
    },
    "section": "",
    "image": "",
    "answer": "a",
    "solution": "",
    "examtype": "wassce",
    "examyear": "2014"
  },
  {
    "id": 47,
    "question": "Which of the following is not a function of the Independent National Electoral Commission (INEC)?",
    "option": {
      "a": "Administering oath of office to elected officers",
      "b": "Conducting periodic elections",
      "c": "Recruitment of electoral officers.",
      "d": "Registration of political parties"
    },
    "section": "",
    "image": "",
    "answer": "a",
    "solution": "",
    "examtype": "neco",
    "examyear": "2014"
  },
  {
    "id": 55,
    "question": "The structure of the Nigerian legislature is - in nature",
    "option": {
      "a": "bicameral",
      "b": "confederal",
      "c": "federal",
      "d": "unicameral"
    },
    "section": "",
    "image": "",
    "answer": "a",
    "solution": "",
    "examtype": "neco",
    "examyear": "2014"
  },
  {
    "id": 107,
    "question": "The following are duties to be performed by the citizens of a country EXCEPT",
    "option": {
      "a": "Destroying government properties",
      "b": "obey law and order",
      "c": "payment of tax",
      "d": "show loyalty"
    },
    "section": "",
    "image": "",
    "answer": "a",
    "solution": "",
    "examtype": "wassce",
    "examyear": "2012"
  },
  {
    "id": 152,
    "question": "In Nigeria, The agency mainly responsible for the maintenance of internal peace and security is the",
    "option": {
      "a": "Army",
      "b": "Navy",
      "c": "Civil  defense corps",
      "d": "Police"
    },
    "section": "",
    "image": "",
    "answer": "d",
    "solution": "",
    "examtype": "neco",
    "examyear": "2012"
  },
  {
    "id": 164,
    "question": "Public servants in Nigeria belong to the ............. arm of government",
    "option": {
      "a": "military",
      "b": "executive",
      "c": "legislature",
      "d": "judiciary"
    },
    "section": "",
    "image": "",
    "answer": "b",
    "solution": "",
    "examtype": "neco",
    "examyear": "2012"
  },
  {
    "id": 182,
    "question": "A manifesto refers to",
    "option": {
      "a": "the register of party members",
      "b": "rejected ballot papers",
      "c": "valid ballot papers",
      "d": "Document containing the aims and programmes of   a political party"
    },
    "section": "",
    "image": "",
    "answer": "d",
    "solution": "",
    "examtype": "neco",
    "examyear": "2012"
  },
  {
    "id": 192,
    "question": "Colonization of Africa was mainly motivated by",
    "option": {
      "a": "security consideration",
      "b": "economic reasons",
      "c": "religious reasons",
      "d": "cultural factor"
    },
    "section": "",
    "image": "",
    "answer": "b",
    "solution": "",
    "examtype": "neco",
    "examyear": "2012"
  },
  {
    "id": 223,
    "question": "Which of the following constitutes drug abuse",
    "option": {
      "a": "taking less than the dose recommended by the doctor",
      "b": "taking more than the dose recommended by the doctor",
      "c": "taking the exact dose recommended by the doctor",
      "d": "A and B above"
    },
    "section": "",
    "image": "",
    "answer": "d",
    "solution": "",
    "examtype": "wassce",
    "examyear": "2013"
  },
  {
    "id": 237,
    "question": "Popular participation refers to",
    "option": {
      "a": "Political Apathy",
      "b": "The active involvement of citizens in the social political activities of a country",
      "c": "The rule of the party with the largest number of supporters",
      "d": "The rule of a prominent and popular politician"
    },
    "section": "",
    "image": "",
    "answer": "b",
    "solution": "",
    "examtype": "wassce",
    "examyear": "2013"
  },
  {
    "id": 239,
    "question": "Cultism is ........, and so it should be ........",
    "option": {
      "a": "useful - allowed",
      "b": "cultural - encouraged",
      "c": "dangerous - discouraged",
      "d": "amiable - supported"
    },
    "section": "",
    "image": "",
    "answer": "c",
    "solution": "",
    "examtype": "wassce",
    "examyear": "2013"
  },
  {
    "id": 241,
    "question": "A problem commonly faced by most people living with HIV/AIDs is of",
    "option": {
      "a": "Stigmatization",
      "b": "Non availability of drugs",
      "c": "Government insincerity",
      "d": "Lost of appetite"
    },
    "section": "",
    "image": "",
    "answer": "a",
    "solution": "",
    "examtype": "wassce",
    "examyear": "2013"
  },
  {
    "id": 250,
    "question": "When a constitution is difficult to amend it is said to be",
    "option": {
      "a": "rigid",
      "b": "flexible",
      "c": "written",
      "d": "federal"
    },
    "section": "",
    "image": "",
    "answer": "a",
    "solution": "",
    "examtype": "neco",
    "examyear": "2013"
  },
  {
    "id": 263,
    "question": "In which of the following system is survival of the fittest mostly practiced",
    "option": {
      "a": "Communist system",
      "b": "Capitalist system",
      "c": "Feudalist",
      "d": "Totalistic system"
    },
    "section": "",
    "image": "",
    "answer": "b",
    "solution": "",
    "examtype": "neco",
    "examyear": "2013"
  },
  {
    "id": 295,
    "question": "Human traffickers usually force their victims to engage in",
    "option": {
      "a": "rewarding exercise",
      "b": "religious activities",
      "c": "forced labour",
      "d": "useful trade"
    },
    "section": "",
    "image": "",
    "answer": "c",
    "solution": "",
    "examtype": "wassce",
    "examyear": "2011"
  },
  {
    "id": 334,
    "question": "Which of the following is true",
    "option": {
      "a": "The CD (Community Development) exercise   embarked by corpers is not paid for by the community",
      "b": "Corpers collect extra money for embarking on the C.D",
      "c": "Corpers are not usually given monthly allowances",
      "d": "The aim of the NYSC scheme is to foster disunity   in the country"
    },
    "section": "",
    "image": "",
    "answer": "a",
    "solution": "",
    "examtype": "wassce",
    "examyear": "2011"
  },
  {
    "id": 383,
    "question": "Which of the following can not be easily abused?",
    "option": {
      "a": "Cosmetics",
      "b": "Stimulant",
      "c": "Tobacco",
      "d": "Narcotics"
    },
    "section": "",
    "image": "",
    "answer": "a",
    "solution": "",
    "examtype": "wassce",
    "examyear": "2016"
  },
  {
    "id": 425,
    "question": "Democracy can promote national development if there is",
    "option": {
      "a": "good governance",
      "b": "promotion of culture",
      "c": "immunity for leaders",
      "d": "registration of parties"
    },
    "section": "",
    "image": "",
    "answer": "a",
    "solution": "",
    "examtype": "wassce",
    "examyear": "2015"
  }
]